more.jinja2-0.3-py3.8-nspkg.pth
more/jinja2/__init__.py
more/jinja2/main.py
more/jinja2/tests/__init__.py
more/jinja2/tests/test_jinja2.py
more/jinja2/tests/fixtures/__init__.py
more/jinja2/tests/fixtures/override_template.py
more/jinja2/tests/fixtures/override_template_inheritance.py
more/jinja2/tests/fixtures/template.py
more/jinja2/tests/fixtures/template_inheritance.py
more/jinja2/tests/fixtures/templates/base.jinja2
more/jinja2/tests/fixtures/templates/person.jinja2
more/jinja2/tests/fixtures/templates/person_inherit.jinja2
more/jinja2/tests/fixtures/templates_override/base.jinja2
more/jinja2/tests/fixtures/templates_override/person.jinja2
more.jinja2-0.3.dist-info/LICENSE.txt
more.jinja2-0.3.dist-info/METADATA
more.jinja2-0.3.dist-info/WHEEL
more.jinja2-0.3.dist-info/namespace_packages.txt
more.jinja2-0.3.dist-info/top_level.txt
more.jinja2-0.3.dist-info/RECORD
