Metadata-Version: 2.1
Name: more.jinja2
Version: 0.3
Summary: Jinja2 template integration for Morepath
Home-page: https://github.com/morepath/more.jinja2
Author: Martijn Faassen
Author-email: faassen@startifact.com
License: BSD
Keywords: morepath jinja2
Classifier: License :: OSI Approved :: BSD License
Classifier: Programming Language :: Python :: 3
Classifier: Programming Language :: Python :: 3.6
Classifier: Programming Language :: Python :: 3.7
Classifier: Programming Language :: Python :: 3.8
Classifier: Programming Language :: Python :: 3.9
Classifier: Programming Language :: Python :: 3.10
Requires-Python: >=3.6
License-File: LICENSE.txt
Requires-Dist: setuptools
Requires-Dist: morepath (>=0.15)
Requires-Dist: Jinja2 (>=2.9)
Provides-Extra: test
Requires-Dist: pytest (>=7) ; extra == 'test'
Requires-Dist: pytest-cov ; extra == 'test'
Requires-Dist: WebTest ; extra == 'test'
